fanstatic-stubs/METADATA.toml
fanstatic-stubs/__init__.pyi
fanstatic-stubs/checksum.pyi
fanstatic-stubs/compiler.pyi
fanstatic-stubs/config.pyi
fanstatic-stubs/core.pyi
fanstatic-stubs/inclusion.pyi
fanstatic-stubs/injector.pyi
fanstatic-stubs/publisher.pyi
fanstatic-stubs/py.typed
fanstatic-stubs/registry.pyi
fanstatic-stubs/wsgi.pyi
types_fanstatic-1.5.0.20250822.dist-info/licenses/LICENSE
types_fanstatic-1.5.0.20250822.dist-info/METADATA
types_fanstatic-1.5.0.20250822.dist-info/WHEEL
types_fanstatic-1.5.0.20250822.dist-info/top_level.txt
types_fanstatic-1.5.0.20250822.dist-info/RECORD
